eva3d/__init__.py
eva3d-0.0.1.dev0.dist-info/METADATA
eva3d-0.0.1.dev0.dist-info/WHEEL
eva3d-0.0.1.dev0.dist-info/top_level.txt
eva3d-0.0.1.dev0.dist-info/RECORD
